cmap_wsxmTopy/__init__.py
cmap_wsxmTopy/examples/Julio.lut
cmap_wsxmTopy/examples/lut_to_py.py
cmap_wsxmTopy/examples/py_to_lut.py
cmap_wsxmTopy/examples/viridis.ipynb
cmap_wsxmTopy/examples/viridis.lut
cmap_wsxmTopy/out/output_colormap.lut
cmap_wsxmTopy/src/converter.py
cmap_wsxmtopy-0.0.9.dist-info/METADATA
cmap_wsxmtopy-0.0.9.dist-info/WHEEL
cmap_wsxmtopy-0.0.9.dist-info/RECORD
