Metadata-Version: 2.3
Name: cmap_wsxmTopy
Version: 0.0.9
Summary: convert wsxm cmap files to python compatible format
License: MIT
Author: stefanotriv
Author-email: s.trivini@nanogune.eu
Requires-Python: >=3.9,<4.0
Classifier: License :: OSI Approved :: MIT License
Classifier: Programming Language :: Python :: 3
Classifier: Programming Language :: Python :: 3.9
Classifier: Programming Language :: Python :: 3.10
Classifier: Programming Language :: Python :: 3.11
Classifier: Programming Language :: Python :: 3.12
Classifier: Programming Language :: Python :: 3.13
Project-URL: Homepage, https://github.com/stefanotriv/cmap_wsxmTopy
